fastauth/__init__.py
fast_authentication-0.0.1.dist-info/LICENSE
fast_authentication-0.0.1.dist-info/METADATA
fast_authentication-0.0.1.dist-info/WHEEL
fast_authentication-0.0.1.dist-info/RECORD
