Metadata-Version: 2.1
Name: fast-authentication
Version: 0.0.1
Summary: Extensible authentication library for FastAPI
Author: vipierozan99
Author-email: victorpierozan@gmail.com
Requires-Python: >=3.10,<4.0
Classifier: Programming Language :: Python :: 3
Classifier: Programming Language :: Python :: 3.10
Classifier: Programming Language :: Python :: 3.11
